{"version": 0.6, "generator": "Overpass API 0.7.62.5 1bd436f1", "osm3s": {"timestamp_osm_base": "2025-03-23T23:22:29Z", "copyright": "The data included in this document is from www.openstreetmap.org. The data is made available under ODbL."}, "elements": [{"type": "node", "id": 499122827, "lat": 41.4304493, "lon": 2.1743213, "tags": {"addr:housenumber": "266", "addr:postcode": "08031", "addr:street": "Passeig de Fabra i Puig", "alt_name": "Restaurant Bar Chirimas", "amenity": "bar", "name": "Chiribito"}}, {"type": "node", "id": 499122828, "lat": 41.4319753, "lon": 2.1737066, "tags": {"amenity": "bar", "name": "La Flor", "name:ca": "La Flor"}}, {"type": "node", "id": 939088342, "lat": 41.4225474, "lon": 2.1794557, "tags": {"addr:city": "Barcelona", "addr:housenumber": "8", "addr:postcode": "08027", "addr:street": "Carrer de la Manigua", "alcohol": "beer", "amenity": "bar", "contact:phone": "+34661230209", "drink:beer": "retail", "drink:club-mate": "retail", "name": "2D2Dspuma", "opening_hours": "Mo-Th 18:00-23:30; Fr,Sa 18:00-01:30", "shop": "alcohol", "website": "https://www.2d2dspuma.com/", "wifi": "no"}}, {"type": "node", "id": 1458948844, "lat": 41.4324873, "lon": 2.180298, "tags": {"amenity": "bar", "name": "Bar Hot Dog City", "source": "survey", "wifi": "no"}}, {"type": "node", "id": 1466014012, "lat": 41.4312348, "lon": 2.1805713, "tags": {"amenity": "bar", "internet_access": "wlan", "internet_access:access": "customers", "internet_access:fee": "no", "name": "MAXI & MAX", "source": "knowledge"}}, {"type": "node", "id": 2063950766, "lat": 41.4292996, "lon": 2.1822972, "tags": {"amenity": "bar"}}, {"type": "node", "id": 2063950771, "lat": 41.4295591, "lon": 2.1811277, "tags": {"amenity": "bar"}}, {"type": "node", "id": 2063950777, "lat": 41.4293038, "lon": 2.182678, "tags": {"amenity": "bar"}}, {"type": "node", "id": 2063950809, "lat": 41.4295209, "lon": 2.1823293, "tags": {"amenity": "bar"}}, {"type": "node", "id": 2063950839, "lat": 41.4297482, "lon": 2.1818894, "tags": {"amenity": "bar"}}, {"type": "node", "id": 2402571530, "lat": 41.4148588, "lon": 2.1946058, "tags": {"addr:city": "Barcelona", "amenity": "bar", "name": "El Manolo", "opening_hours": "Mo-Fr 07:00-01:00; Sa,Su,PH 08:00-02:30", "smoking": "outside", "wheelchair": "yes"}}, {"type": "node", "id": 3009193595, "lat": 41.4226674, "lon": 2.1804216, "tags": {"amenity": "bar", "name": "Torre Rosa", "name:ca": "Torre Rosa"}}, {"type": "node", "id": 3049395452, "lat": 41.4132792, "lon": 2.1904648, "tags": {"amenity": "bar", "cuisine": "spanish;tea;sandwich;coffee_shop", "name": "Luar"}}, {"type": "node", "id": 3157278771, "lat": 41.4141072, "lon": 2.1811729, "tags": {"amenity": "bar", "name": "L'Ombra"}}, {"type": "node", "id": 3586001258, "lat": 41.4117301, "lon": 2.1784624, "tags": {"addr:housenumber": "362", "addr:street": "Carrer de la Independ\u00e8ncia", "amenity": "bar", "name": "Los Panda Lounge", "payment:coins": "yes"}}, {"type": "node", "id": 4441805790, "lat": 41.4125412, "lon": 2.1902351, "tags": {"addr:postcode": "08027", "addr:street": "Carrer de Las Navas de Tolosa", "amenity": "bar", "cuisine": "sandwich;local;coffee_shop", "name": "Montferry", "name:ca": "Montferry"}}, {"type": "node", "id": 4719232493, "lat": 41.4167464, "lon": 2.1806391, "tags": {"amenity": "bar", "name": "Wei", "name:es": "Bar Wei"}}, {"type": "node", "id": 4721515999, "lat": 41.4181616, "lon": 2.1725485, "tags": {"amenity": "bar", "name": "Cowboy", "name:es": "Cowboy"}}, {"type": "node", "id": 4721516009, "lat": 41.4204705, "lon": 2.1820513, "tags": {"addr:housenumber": "7", "addr:postcode": "08027", "addr:street": "Carrer d'Olesa", "amenity": "bar", "name": "Collonut", "opening_hours": "17:00-24:00; Sa-Su 11:00-17:00", "phone": "+34937634351", "toilets:wheelchair": "no", "website": "http://collonut.com", "wheelchair": "limited"}}, {"type": "node", "id": 4721519794, "lat": 41.4182723, "lon": 2.1807695, "tags": {"amenity": "bar", "name": "El Timbalet", "name:es": "El Timbalet"}}, {"type": "node", "id": 4721521995, "lat": 41.421516, "lon": 2.1797115, "tags": {"amenity": "bar", "name": "Charly", "name:es": "Charly"}}, {"type": "node", "id": 4721547992, "lat": 41.41913, "lon": 2.1723528, "tags": {"amenity": "bar", "name": "El raconet", "name:es": "El raconet", "smoking": "outside"}}, {"type": "node", "id": 4721548093, "lat": 41.41757, "lon": 2.1807367, "tags": {"amenity": "bar", "name": "Aqu\u00ed Em Quedo", "name:ca": "Aqu\u00ed Em Quedo"}}, {"type": "node", "id": 4726092789, "lat": 41.4179517, "lon": 2.1771754, "tags": {"amenity": "bar", "name": "Bodega Ani", "name:es": "Bodega Ani"}}, {"type": "node", "id": 4726136490, "lat": 41.4193244, "lon": 2.1757557, "tags": {"amenity": "bar", "name": "Reca's", "name:es": "Reca's"}}, {"type": "node", "id": 4727954092, "lat": 41.4131841, "lon": 2.1814167, "tags": {"amenity": "bar", "name": "Lluna Plena", "name:ca": "Lluna Plena", "name:es": "Lluna Plena"}}, {"type": "node", "id": 4727965491, "lat": 41.4143734, "lon": 2.1817362, "tags": {"amenity": "bar", "name": "2 Hermanos", "name:es": "2 Hermanos"}}, {"type": "node", "id": 4728093792, "lat": 41.4122174, "lon": 2.180827, "tags": {"amenity": "bar", "name": "La Uni\u00f3n", "name:es": "La Uni\u00f3n"}}, {"type": "node", "id": 4729342899, "lat": 41.418226, "lon": 2.1772147, "tags": {"amenity": "bar", "name": "Taverna El Ficus", "name:ca": "Taverna El Ficus"}}, {"type": "node", "id": 4729342991, "lat": 41.4173855, "lon": 2.1748057, "tags": {"amenity": "bar", "name": "Pirineo", "name:es": "Pirineo"}}, {"type": "node", "id": 4762861732, "lat": 41.4242713, "lon": 2.1819304, "tags": {"amenity": "bar", "name": "Can Alexandre", "name:ca": "Can Alexandre"}}, {"type": "node", "id": 4762864131, "lat": 41.4240333, "lon": 2.1818107, "tags": {"amenity": "bar", "name": "Puerto Pr\u00edncipe", "name:es": "Puerto Pr\u00edncipe"}}, {"type": "node", "id": 4762934626, "lat": 41.4214873, "lon": 2.1810678, "tags": {"amenity": "bar", "name": "Congr\u00e9s", "name:ca": "Congr\u00e9s"}}, {"type": "node", "id": 4771286821, "lat": 41.4143118, "lon": 2.1807086, "tags": {"amenity": "bar", "name": "Frankfurt", "name:ca": "Frankfurt", "name:es": "Frankfurt"}}, {"type": "node", "id": 4771287021, "lat": 41.4185801, "lon": 2.180734, "tags": {"addr:housenumber": "78", "addr:street": "Passeig de Maragall", "amenity": "bar", "name": "Maragall 78", "name:ca": "Maragall 78"}}, {"type": "node", "id": 4776358125, "lat": 41.4126587, "lon": 2.1767507, "tags": {"amenity": "bar", "name": "Cruzeiro", "name:es": "Cruzeiro", "wheelchair": "no"}}, {"type": "node", "id": 4776358127, "lat": 41.415462, "lon": 2.1807791, "tags": {"amenity": "bar", "name": "Tapitas", "name:es": "Tapitas"}}, {"type": "node", "id": 4776361636, "lat": 41.4134869, "lon": 2.1778053, "tags": {"amenity": "bar", "name": "SQ-47", "name:es": "SQ-47"}}, {"type": "node", "id": 4776374526, "lat": 41.4149461, "lon": 2.1791262, "tags": {"amenity": "bar", "name": "Asian Tapas", "name:es": "Asian Tapas"}}, {"type": "node", "id": 4777016724, "lat": 41.4144356, "lon": 2.1821491, "tags": {"amenity": "bar", "name": "Granja", "name:ca": "Granja", "name:es": "Granja"}}, {"type": "node", "id": 4777261022, "lat": 41.4148432, "lon": 2.188039, "tags": {"amenity": "bar", "name": "Cervecer\u00eda Novo", "name:es": "Cervecer\u00eda Novo"}}, {"type": "node", "id": 4779817136, "lat": 41.415353, "lon": 2.1893165, "tags": {"amenity": "bar", "name": "Bar Petit", "name:ca": "Bar Petit"}}, {"type": "node", "id": 4779817139, "lat": 41.4130954, "lon": 2.1806328, "tags": {"amenity": "bar", "name": "Pika Tapa", "name:es": "Pika Tapa"}}, {"type": "node", "id": 4779864528, "lat": 41.4153311, "lon": 2.1887063, "tags": {"amenity": "bar", "name": "Bar Jordi", "name:ca": "Bar Jordi"}}, {"type": "node", "id": 4789751822, "lat": 41.4142674, "lon": 2.180649, "tags": {"amenity": "bar", "name": "Lisboa", "name:es": "Lisboa"}}, {"type": "node", "id": 4860084426, "lat": 41.415497, "lon": 2.1816972, "tags": {"amenity": "bar", "name": "En Bandeja", "name:es": "En Bandeja"}}, {"type": "node", "id": 4860084427, "lat": 41.4182252, "lon": 2.1808719, "tags": {"amenity": "bar", "name": "Vilari\u00f1o", "name:es": "Vilari\u00f1o"}}, {"type": "node", "id": 5156647128, "lat": 41.415065, "lon": 2.1896641, "tags": {"addr:city": "Barcelona", "addr:postcode": "08027", "addr:street": "Carrer de Biscaia", "amenity": "bar", "brewery": "yes", "name": "Bar 340", "old_name": "Bar Koala"}}, {"type": "node", "id": 5156690624, "lat": 41.4156111, "lon": 2.1907072, "tags": {"addr:street": "Carrer d'Espronceda", "amenity": "bar", "name": "Salseta del Clot", "name:ca": "Salseta del Clot"}}, {"type": "node", "id": 5156691328, "lat": 41.4134452, "lon": 2.1895948, "tags": {"addr:street": "Carrer de Las Navas de Tolosa", "amenity": "bar", "name": "Bodega la Taberna", "name:ca": "Bodega la Taberna"}}, {"type": "node", "id": 5200135128, "lat": 41.4200262, "lon": 2.1873281, "tags": {"addr:street": "Carrer de Felip II", "amenity": "bar", "name": "Tro-BAR-se", "name:ca": "Tro-BAR-se"}}, {"type": "node", "id": 5200142525, "lat": 41.4197567, "lon": 2.1875472, "tags": {"addr:street": "Carrer de Felip II", "amenity": "bar", "name": "Granja Bar Gero's", "name:ca": "Granja Bar Gero's"}}, {"type": "node", "id": 5200151922, "lat": 41.4194132, "lon": 2.1879316, "tags": {"addr:street": "Carrer de Felip II", "amenity": "bar", "name": "La Giralda", "name:ca": "La Giralda"}}, {"type": "node", "id": 5200151926, "lat": 41.4177111, "lon": 2.1877943, "tags": {"amenity": "bar", "name": "Stuttgart", "name:ca": "Stuttgart", "wheelchair": "yes"}}, {"type": "node", "id": 5200163223, "lat": 41.4167821, "lon": 2.1872237, "tags": {"addr:street": "Avinguda Meridiana", "amenity": "bar", "name": "Megabar", "name:ca": "Megabar"}}, {"type": "node", "id": 5200163224, "lat": 41.4160433, "lon": 2.1872689, "tags": {"addr:street": "Avinguda Meridiana", "amenity": "bar", "name": "2veinte", "name:ca": "2veinte"}}, {"type": "node", "id": 5200163921, "lat": 41.4175801, "lon": 2.1884489, "tags": {"addr:street": "Carrer d'Espronceda", "amenity": "bar", "name": "M\u00e1ximo", "name:ca": "M\u00e1ximo"}}, {"type": "node", "id": 5271863061, "lat": 41.4325001, "lon": 2.1835043, "tags": {"amenity": "bar", "name": "Bar Meridiana"}}, {"type": "node", "id": 5510666721, "lat": 41.4222467, "lon": 2.1786712, "tags": {"amenity": "bar", "name": "Yaniz", "name:ca": "Yaniz"}}, {"type": "node", "id": 5510666722, "lat": 41.4227174, "lon": 2.1774511, "tags": {"addr:street": "Carrer del Segle XX", "amenity": "bar", "name": "Bar-celona", "name:ca": "Bar-celona"}}, {"type": "node", "id": 5820816754, "lat": 41.4263927, "lon": 2.1910973, "tags": {"amenity": "bar"}}, {"type": "node", "id": 5820816854, "lat": 41.4279119, "lon": 2.1906334, "tags": {"addr:street": "Carrer Gran de Sant Andreu", "amenity": "bar", "name": "L'ideal"}}, {"type": "node", "id": 5868581785, "lat": 41.4191026, "lon": 2.1801533, "tags": {"amenity": "bar", "name": "El Traga ti\u00f3"}}, {"type": "node", "id": 5961171186, "lat": 41.4304182, "lon": 2.1879027, "tags": {"amenity": "bar", "name": "Bar La Casa de les Monges"}}, {"type": "node", "id": 6635908485, "lat": 41.4289931, "lon": 2.1843214, "tags": {"amenity": "bar", "name": "Los Faunos"}}, {"type": "node", "id": 10695734808, "lat": 41.4134561, "lon": 2.1694985, "tags": {"addr:city": "Barcelona", "addr:housenumber": "69", "addr:postcode": "08024", "addr:street": "Ronda del Guinard\u00f3", "amenity": "bar", "name": "La Perla", "opening_hours": "Mo-Fr 07:00-16:00; Su 08:00-14:00"}}, {"type": "node", "id": 11300085394, "lat": 41.4244918, "lon": 2.1930221, "tags": {"addr:city": "Barcelona", "addr:housenumber": "1-11", "addr:postcode": "08027", "addr:street": "Carrer de Ferran Turn\u00e9", "amenity": "bar", "contact:phone": "+34931863859", "contact:website": "https://www.mescladis.org/noticia/mescladis-bostik", "contact:whatsapp": "+34605056870", "description": "Mesclad\u00eds Bostik es un espacio socio gastron\u00f3mico no lucrativo, con una propuesta formativa, solidaria, inclusiva y comunitaria.", "description:es": "Mesclad\u00eds Bostik es un espacio socio gastron\u00f3mico no lucrativo, con una propuesta formativa, solidaria, inclusiva y comunitaria.", "name": "Mesclad\u00eds Bostik"}}, {"type": "node", "id": 11492637390, "lat": 41.4163131, "lon": 2.172093, "tags": {"addr:city": "Barcelona", "addr:postcode": "08041", "addr:street": "Passatge del Torrent d'en Melis", "amenity": "bar", "name": "Bar Centre C\u00edvic Guinard\u00f3", "phone": "+34 657 82 99 45", "website": "https://ajuntament.barcelona.cat/ccivics/guinardo/bar/"}}, {"type": "node", "id": 11704441798, "lat": 41.4173037, "lon": 2.1704767, "tags": {"addr:city": "Barcelona", "addr:housenumber": "9", "addr:postcode": "08041", "addr:street": "Carrer de G\u00e8nova", "amenity": "bar", "name": "Bar Antonio", "opening_hours": "Mo-Fr 07:00-20:00"}}, {"type": "node", "id": 11927931595, "lat": 41.4207005, "lon": 2.1809584, "tags": {"amenity": "bar", "name": "Olaf"}}, {"type": "node", "id": 12400373415, "lat": 41.4177606, "lon": 2.1712845, "tags": {"addr:city": "Barcelona", "addr:housenumber": "163", "addr:postcode": "08041", "addr:street": "Avinguda de la Mare de D\u00e9u de Montserrat", "amenity": "bar", "name": "Bar Mu\u00f1oz", "opening_hours": "Mo-Su 00:00-01:00,06:30-00:00", "outdoor_seating": "yes"}}]}